bitbrowser_api/__init__.py
bitbrowser_api/bitbrowser_api.py
bitbrowser_api-0.5.dist-info/LICENSE
bitbrowser_api-0.5.dist-info/METADATA
bitbrowser_api-0.5.dist-info/WHEEL
bitbrowser_api-0.5.dist-info/top_level.txt
bitbrowser_api-0.5.dist-info/RECORD
