Metadata-Version: 2.1
Name: bitbrowser_api
Version: 0.5
Summary: This is a bitbrowser operation tool
Home-page: https://github.com/ox-blueblue/bitbrowser_api
Author: blue
Author-email: embzhengblue@gmail.com
Project-URL: Source, https://github.com/embzheng/bitbrowser_api
Classifier: Programming Language :: Python :: 3
Classifier: License :: OSI Approved :: MIT License
Classifier: Operating System :: OS Independent
License-File: LICENSE
Requires-Dist: requests
